<annotation>
	<folder>TF_DATA2</folder>
	<filename>c357.jpg</filename>
	<path>C:\Users\Thanh Ho\Pictures\FreeVideoToJPGConverter\TF_DATA2\c357.jpg</path>
	<source>
		<database>Unknown</database>
	</source>
	<size>
		<width>1920</width>
		<height>852</height>
		<depth>3</depth>
	</size>
	<segmented>0</segmented>
	<object>
		<name>xe_ban_tai</name>
		<pose>Unspecified</pose>
		<truncated>0</truncated>
		<difficult>0</difficult>
		<bndbox>
			<xmin>1370</xmin>
			<ymin>498</ymin>
			<xmax>1589</xmax>
			<ymax>722</ymax>
		</bndbox>
	</object>
	<object>
		<name>xe_may</name>
		<pose>Unspecified</pose>
		<truncated>0</truncated>
		<difficult>0</difficult>
		<bndbox>
			<xmin>1352</xmin>
			<ymin>437</ymin>
			<xmax>1460</xmax>
			<ymax>507</ymax>
		</bndbox>
	</object>
	<object>
		<name>xe_may</name>
		<pose>Unspecified</pose>
		<truncated>0</truncated>
		<difficult>0</difficult>
		<bndbox>
			<xmin>1778</xmin>
			<ymin>466</ymin>
			<xmax>1836</xmax>
			<ymax>528</ymax>
		</bndbox>
	</object>
	<object>
		<name>xe_may</name>
		<pose>Unspecified</pose>
		<truncated>0</truncated>
		<difficult>0</difficult>
		<bndbox>
			<xmin>1686</xmin>
			<ymin>383</ymin>
			<xmax>1730</xmax>
			<ymax>456</ymax>
		</bndbox>
	</object>
	<object>
		<name>xe_may</name>
		<pose>Unspecified</pose>
		<truncated>0</truncated>
		<difficult>0</difficult>
		<bndbox>
			<xmin>1429</xmin>
			<ymin>260</ymin>
			<xmax>1471</xmax>
			<ymax>313</ymax>
		</bndbox>
	</object>
	<object>
		<name>xe_hoi</name>
		<pose>Unspecified</pose>
		<truncated>0</truncated>
		<difficult>0</difficult>
		<bndbox>
			<xmin>1232</xmin>
			<ymin>247</ymin>
			<xmax>1347</xmax>
			<ymax>347</ymax>
		</bndbox>
	</object>
	<object>
		<name>xe_hoi</name>
		<pose>Unspecified</pose>
		<truncated>0</truncated>
		<difficult>0</difficult>
		<bndbox>
			<xmin>1404</xmin>
			<ymin>206</ymin>
			<xmax>1501</xmax>
			<ymax>260</ymax>
		</bndbox>
	</object>
	<object>
		<name>xe_hoi</name>
		<pose>Unspecified</pose>
		<truncated>0</truncated>
		<difficult>0</difficult>
		<bndbox>
			<xmin>1108</xmin>
			<ymin>377</ymin>
			<xmax>1288</xmax>
			<ymax>509</ymax>
		</bndbox>
	</object>
	<object>
		<name>xe_hoi</name>
		<pose>Unspecified</pose>
		<truncated>0</truncated>
		<difficult>0</difficult>
		<bndbox>
			<xmin>1639</xmin>
			<ymin>524</ymin>
			<xmax>1837</xmax>
			<ymax>704</ymax>
		</bndbox>
	</object>
	<object>
		<name>xe_hoi</name>
		<pose>Unspecified</pose>
		<truncated>0</truncated>
		<difficult>0</difficult>
		<bndbox>
			<xmin>1454</xmin>
			<ymin>311</ymin>
			<xmax>1575</xmax>
			<ymax>401</ymax>
		</bndbox>
	</object>
	<object>
		<name>xe_hoi</name>
		<pose>Unspecified</pose>
		<truncated>0</truncated>
		<difficult>0</difficult>
		<bndbox>
			<xmin>1502</xmin>
			<ymin>252</ymin>
			<xmax>1601</xmax>
			<ymax>311</ymax>
		</bndbox>
	</object>
	<object>
		<name>xe_hoi</name>
		<pose>Unspecified</pose>
		<truncated>0</truncated>
		<difficult>0</difficult>
		<bndbox>
			<xmin>1354</xmin>
			<ymin>138</ymin>
			<xmax>1429</xmax>
			<ymax>196</ymax>
		</bndbox>
	</object>
	<object>
		<name>xe_tai</name>
		<pose>Unspecified</pose>
		<truncated>0</truncated>
		<difficult>0</difficult>
		<bndbox>
			<xmin>1520</xmin>
			<ymin>151</ymin>
			<xmax>1616</xmax>
			<ymax>246</ymax>
		</bndbox>
	</object>
	<object>
		<name>xe_tai</name>
		<pose>Unspecified</pose>
		<truncated>0</truncated>
		<difficult>0</difficult>
		<bndbox>
			<xmin>1447</xmin>
			<ymin>124</ymin>
			<xmax>1538</xmax>
			<ymax>204</ymax>
		</bndbox>
	</object>
</annotation>
