<annotation>
	<folder>TF_DATA2</folder>
	<filename>c392.jpg</filename>
	<path>C:\Users\Thanh Ho\Pictures\FreeVideoToJPGConverter\TF_DATA2\c392.jpg</path>
	<source>
		<database>Unknown</database>
	</source>
	<size>
		<width>1920</width>
		<height>852</height>
		<depth>3</depth>
	</size>
	<segmented>0</segmented>
	<object>
		<name>xe_may</name>
		<pose>Unspecified</pose>
		<truncated>0</truncated>
		<difficult>0</difficult>
		<bndbox>
			<xmin>1333</xmin>
			<ymin>483</ymin>
			<xmax>1401</xmax>
			<ymax>609</ymax>
		</bndbox>
	</object>
	<object>
		<name>xe_may</name>
		<pose>Unspecified</pose>
		<truncated>0</truncated>
		<difficult>0</difficult>
		<bndbox>
			<xmin>1232</xmin>
			<ymin>496</ymin>
			<xmax>1300</xmax>
			<ymax>586</ymax>
		</bndbox>
	</object>
	<object>
		<name>xe_may</name>
		<pose>Unspecified</pose>
		<truncated>0</truncated>
		<difficult>0</difficult>
		<bndbox>
			<xmin>1188</xmin>
			<ymin>377</ymin>
			<xmax>1246</xmax>
			<ymax>472</ymax>
		</bndbox>
	</object>
	<object>
		<name>xe_may</name>
		<pose>Unspecified</pose>
		<truncated>0</truncated>
		<difficult>0</difficult>
		<bndbox>
			<xmin>418</xmin>
			<ymin>328</ymin>
			<xmax>487</xmax>
			<ymax>383</ymax>
		</bndbox>
	</object>
	<object>
		<name>xe_may</name>
		<pose>Unspecified</pose>
		<truncated>0</truncated>
		<difficult>0</difficult>
		<bndbox>
			<xmin>280</xmin>
			<ymin>452</ymin>
			<xmax>332</xmax>
			<ymax>545</ymax>
		</bndbox>
	</object>
	<object>
		<name>xe_may</name>
		<pose>Unspecified</pose>
		<truncated>0</truncated>
		<difficult>0</difficult>
		<bndbox>
			<xmin>338</xmin>
			<ymin>611</ymin>
			<xmax>419</xmax>
			<ymax>727</ymax>
		</bndbox>
	</object>
	<object>
		<name>xe_may</name>
		<pose>Unspecified</pose>
		<truncated>0</truncated>
		<difficult>0</difficult>
		<bndbox>
			<xmin>1395</xmin>
			<ymin>255</ymin>
			<xmax>1438</xmax>
			<ymax>324</ymax>
		</bndbox>
	</object>
	<object>
		<name>xe_hoi</name>
		<pose>Unspecified</pose>
		<truncated>0</truncated>
		<difficult>0</difficult>
		<bndbox>
			<xmin>956</xmin>
			<ymin>393</ymin>
			<xmax>1132</xmax>
			<ymax>493</ymax>
		</bndbox>
	</object>
	<object>
		<name>xe_hoi</name>
		<pose>Unspecified</pose>
		<truncated>0</truncated>
		<difficult>0</difficult>
		<bndbox>
			<xmin>1377</xmin>
			<ymin>610</ymin>
			<xmax>1602</xmax>
			<ymax>789</ymax>
		</bndbox>
	</object>
	<object>
		<name>xe_hoi</name>
		<pose>Unspecified</pose>
		<truncated>0</truncated>
		<difficult>0</difficult>
		<bndbox>
			<xmin>877</xmin>
			<ymin>655</ymin>
			<xmax>1193</xmax>
			<ymax>797</ymax>
		</bndbox>
	</object>
	<object>
		<name>xe_hoi</name>
		<pose>Unspecified</pose>
		<truncated>0</truncated>
		<difficult>0</difficult>
		<bndbox>
			<xmin>1496</xmin>
			<ymin>442</ymin>
			<xmax>1645</xmax>
			<ymax>575</ymax>
		</bndbox>
	</object>
	<object>
		<name>xe_hoi</name>
		<pose>Unspecified</pose>
		<truncated>0</truncated>
		<difficult>0</difficult>
		<bndbox>
			<xmin>1445</xmin>
			<ymin>334</ymin>
			<xmax>1569</xmax>
			<ymax>434</ymax>
		</bndbox>
	</object>
	<object>
		<name>xe_hoi</name>
		<pose>Unspecified</pose>
		<truncated>0</truncated>
		<difficult>0</difficult>
		<bndbox>
			<xmin>1478</xmin>
			<ymin>231</ymin>
			<xmax>1543</xmax>
			<ymax>314</ymax>
		</bndbox>
	</object>
	<object>
		<name>xe_khach</name>
		<pose>Unspecified</pose>
		<truncated>0</truncated>
		<difficult>0</difficult>
		<bndbox>
			<xmin>1341</xmin>
			<ymin>195</ymin>
			<xmax>1451</xmax>
			<ymax>282</ymax>
		</bndbox>
	</object>
	<object>
		<name>xe_tai</name>
		<pose>Unspecified</pose>
		<truncated>0</truncated>
		<difficult>0</difficult>
		<bndbox>
			<xmin>1139</xmin>
			<ymin>161</ymin>
			<xmax>1256</xmax>
			<ymax>268</ymax>
		</bndbox>
	</object>
	<object>
		<name>xe_tai</name>
		<pose>Unspecified</pose>
		<truncated>0</truncated>
		<difficult>0</difficult>
		<bndbox>
			<xmin>173</xmin>
			<ymin>305</ymin>
			<xmax>416</xmax>
			<ymax>446</ymax>
		</bndbox>
	</object>
	<object>
		<name>xe_tai</name>
		<pose>Unspecified</pose>
		<truncated>1</truncated>
		<difficult>0</difficult>
		<bndbox>
			<xmin>1668</xmin>
			<ymin>316</ymin>
			<xmax>1920</xmax>
			<ymax>578</ymax>
		</bndbox>
	</object>
</annotation>
