<annotation>
	<folder>TF_DATA1</folder>
	<filename>i210.jpg</filename>
	<path>D:\data\Xe\Chua_label\image\TF_DATA1\i210.jpg</path>
	<source>
		<database>Unknown</database>
	</source>
	<size>
		<width>1920</width>
		<height>1052</height>
		<depth>3</depth>
	</size>
	<segmented>0</segmented>
	<object>
		<name>xe_may</name>
		<pose>Unspecified</pose>
		<truncated>0</truncated>
		<difficult>0</difficult>
		<bndbox>
			<xmin>992</xmin>
			<ymin>613</ymin>
			<xmax>1109</xmax>
			<ymax>720</ymax>
		</bndbox>
	</object>
	<object>
		<name>xe_may</name>
		<pose>Unspecified</pose>
		<truncated>0</truncated>
		<difficult>0</difficult>
		<bndbox>
			<xmin>304</xmin>
			<ymin>463</ymin>
			<xmax>359</xmax>
			<ymax>539</ymax>
		</bndbox>
	</object>
	<object>
		<name>xe_may</name>
		<pose>Unspecified</pose>
		<truncated>0</truncated>
		<difficult>0</difficult>
		<bndbox>
			<xmin>146</xmin>
			<ymin>487</ymin>
			<xmax>225</xmax>
			<ymax>571</ymax>
		</bndbox>
	</object>
	<object>
		<name>xe_tai</name>
		<pose>Unspecified</pose>
		<truncated>0</truncated>
		<difficult>0</difficult>
		<bndbox>
			<xmin>1229</xmin>
			<ymin>627</ymin>
			<xmax>1665</xmax>
			<ymax>986</ymax>
		</bndbox>
	</object>
	<object>
		<name>xe_tai</name>
		<pose>Unspecified</pose>
		<truncated>0</truncated>
		<difficult>0</difficult>
		<bndbox>
			<xmin>240</xmin>
			<ymin>594</ymin>
			<xmax>796</xmax>
			<ymax>998</ymax>
		</bndbox>
	</object>
	<object>
		<name>xe_container</name>
		<pose>Unspecified</pose>
		<truncated>0</truncated>
		<difficult>0</difficult>
		<bndbox>
			<xmin>1087</xmin>
			<ymin>289</ymin>
			<xmax>1291</xmax>
			<ymax>556</ymax>
		</bndbox>
	</object>
	<object>
		<name>xe_container</name>
		<pose>Unspecified</pose>
		<truncated>0</truncated>
		<difficult>0</difficult>
		<bndbox>
			<xmin>753</xmin>
			<ymin>271</ymin>
			<xmax>915</xmax>
			<ymax>487</ymax>
		</bndbox>
	</object>
	<object>
		<name>xe_container</name>
		<pose>Unspecified</pose>
		<truncated>0</truncated>
		<difficult>0</difficult>
		<bndbox>
			<xmin>600</xmin>
			<ymin>231</ymin>
			<xmax>736</xmax>
			<ymax>362</ymax>
		</bndbox>
	</object>
	<object>
		<name>xe_hoi</name>
		<pose>Unspecified</pose>
		<truncated>0</truncated>
		<difficult>0</difficult>
		<bndbox>
			<xmin>640</xmin>
			<ymin>370</ymin>
			<xmax>744</xmax>
			<ymax>451</ymax>
		</bndbox>
	</object>
	<object>
		<name>xe_buyt</name>
		<pose>Unspecified</pose>
		<truncated>0</truncated>
		<difficult>0</difficult>
		<bndbox>
			<xmin>444</xmin>
			<ymin>396</ymin>
			<xmax>644</xmax>
			<ymax>573</ymax>
		</bndbox>
	</object>
	<object>
		<name>xe_buyt</name>
		<pose>Unspecified</pose>
		<truncated>1</truncated>
		<difficult>0</difficult>
		<bndbox>
			<xmin>1473</xmin>
			<ymin>358</ymin>
			<xmax>1920</xmax>
			<ymax>683</ymax>
		</bndbox>
	</object>
	<object>
		<name>xe_khach</name>
		<pose>Unspecified</pose>
		<truncated>0</truncated>
		<difficult>0</difficult>
		<bndbox>
			<xmin>1231</xmin>
			<ymin>351</ymin>
			<xmax>1363</xmax>
			<ymax>444</ymax>
		</bndbox>
	</object>
</annotation>
